README.md
setup.py
quantumtensornetwork/__init__.py
quantumtensornetwork.egg-info/PKG-INFO
quantumtensornetwork.egg-info/SOURCES.txt
quantumtensornetwork.egg-info/dependency_links.txt
quantumtensornetwork.egg-info/requires.txt
quantumtensornetwork.egg-info/top_level.txt
quantumtensornetwork/embeddings/__init__.py
quantumtensornetwork/embeddings/qembedding.py
quantumtensornetwork/gates/__init__.py
quantumtensornetwork/gates/qcircuit.py
quantumtensornetwork/gates/qgate.py
quantumtensornetwork/gates/qmath.py
quantumtensornetwork/gates/qoperator.py
quantumtensornetwork/layers/__init__.py
quantumtensornetwork/layers/qlayer.py
quantumtensornetwork/layers/qlayers.py
quantumtensornetwork/nn/__init__.py
quantumtensornetwork/nn/modules/__init__.py
quantumtensornetwork/nn/modules/qconv.py
quantumtensornetwork/nn/modules/qpooling.py
quantumtensornetwork/nn/modules/qrnn.py
quantumtensornetwork/nn/modules/qtransformer.py