Metadata-Version: 1.0
Name: quantumtensornetwork
Version: 0.0.1
Summary: tensor network for quantum machine learning
Home-page: UNKNOWN
Author: TuringQ
Author-email: UNKNOWN
License: UNKNOWN
Platform: UNKNOWN
